zope/pytestlayer/__init__.py
zope/pytestlayer/_compat.py
zope/pytestlayer/doctest.py
zope/pytestlayer/fixture.py
zope/pytestlayer/layered.py
zope/pytestlayer/plugin.py
zope/pytestlayer/testing.py
zope/pytestlayer/tests/__init__.py
zope/pytestlayer/tests/conftest.py
zope/pytestlayer/tests/test_doctest.py
zope/pytestlayer/tests/test_fixture.py
zope/pytestlayer/tests/test_integration.py
zope/pytestlayer/tests/test_layer.py
zope/pytestlayer/tests/fixture/bad_layer/__init__.py
zope/pytestlayer/tests/fixture/bad_layer/conftest.py
zope/pytestlayer/tests/fixture/bad_layer/test_core.py
zope/pytestlayer/tests/fixture/custom_fixture_name/__init__.py
zope/pytestlayer/tests/fixture/custom_fixture_name/conftest.py
zope/pytestlayer/tests/fixture/custom_fixture_name/test_core.py
zope/pytestlayer/tests/fixture/keep_layer_across_test_classes/__init__.py
zope/pytestlayer/tests/fixture/keep_layer_across_test_classes/conftest.py
zope/pytestlayer/tests/fixture/keep_layer_across_test_classes/test_core.py
zope/pytestlayer/tests/fixture/layers_with_same_name/__init__.py
zope/pytestlayer/tests/fixture/layers_with_same_name/conftest.py
zope/pytestlayer/tests/fixture/layers_with_same_name/test_core.py
zope/pytestlayer/tests/fixture/no_setup_or_teardown/__init__.py
zope/pytestlayer/tests/fixture/no_setup_or_teardown/conftest.py
zope/pytestlayer/tests/fixture/no_setup_or_teardown/test_core.py
zope/pytestlayer/tests/fixture/order_by_layer/__init__.py
zope/pytestlayer/tests/fixture/order_by_layer/conftest.py
zope/pytestlayer/tests/fixture/order_by_layer/test_core.py
zope/pytestlayer/tests/fixture/order_with_layered_suite/__init__.py
zope/pytestlayer/tests/fixture/order_with_layered_suite/conftest.py
zope/pytestlayer/tests/fixture/order_with_layered_suite/foo.txt
zope/pytestlayer/tests/fixture/order_with_layered_suite/foobar.txt
zope/pytestlayer/tests/fixture/order_with_layered_suite/test_core.py
zope/pytestlayer/tests/fixture/session_fixture/__init__.py
zope_pytestlayer-9.0.dist-info/licenses/LICENSE.txt
zope_pytestlayer-9.0.dist-info/METADATA
zope_pytestlayer-9.0.dist-info/WHEEL
zope_pytestlayer-9.0.dist-info/entry_points.txt
zope_pytestlayer-9.0.dist-info/top_level.txt
zope_pytestlayer-9.0.dist-info/RECORD
